Metadata-Version: 2.1
Name: fast-redirect
Version: 1.0.6.1
Summary: fast-redirect redirects domains.
Author-email: Cyberfusion <support@cyberfusion.io>
Project-URL: Source, https://github.com/CyberfusionIO/fast-redirect
Requires-Dist: starlette ==0.38.2
Requires-Dist: uvicorn ==0.30.6
Requires-Dist: validators ==0.33.0
